retratodefases/RetratoDeFases2D.py
retratodefases/RetratoDeFases3D.py
retratodefases/Trayectorias3D.py
retratodefases/__init__.py
retratodefases/sliders.py
retratodefases/exceptions/__init__.py
retratodefases/exceptions/exceptions.py
retratodefases/exceptions/exceptions2D.py
retratodefases/utils/__init__.py
retratodefases/utils/utils.py
retratodefases-0.1.3.data/scripts/retratodefases-exe
retratodefases-0.1.3.dist-info/LICENSE
retratodefases-0.1.3.dist-info/METADATA
retratodefases-0.1.3.dist-info/WHEEL
retratodefases-0.1.3.dist-info/top_level.txt
retratodefases-0.1.3.dist-info/RECORD
