Metadata-Version: 2.1
Name: retratodefases
Version: 0.1.3
Summary: Una librería sencilla para realizar retratos de fases de sistemas 2D y 3D.
Home-page: https://github.com/Loracio/retrato-de-fases
Author: Unai Lería & Víctor Loras
Author-email: unaileria@gmail.com, vhloras@gmail.com
License: MIT License
Platform: UNKNOWN
Classifier: License :: OSI Approved :: MIT License
Classifier: Operating System :: OS Independent
Classifier: Intended Audience :: Education
Classifier: Intended Audience :: Science/Research
Classifier: Topic :: Scientific/Engineering :: Visualization
Classifier: Topic :: Scientific/Engineering :: Physics
Classifier: Topic :: Scientific/Engineering :: Mathematics
Classifier: Topic :: Scientific/Engineering :: Information Analysis
Classifier: Programming Language :: Python
Classifier: Programming Language :: Python :: 3
Classifier: Programming Language :: Python :: 3.6
Classifier: Programming Language :: Python :: 3.7
Classifier: Programming Language :: Python :: 3.8
Classifier: Programming Language :: Python :: 3.9
Requires-Dist: matplotlib (>=3.3)
Requires-Dist: numpy (>=1.19)
